{
    "im_name": "000751.png",
    "city_name": "N/A",
    "im_width": 1224,
    "im_height": 370,
    "sandbox_tags": [],
    "agents": [
        {
            "agent_img_id": "agent_1",
            "uuid": "d8597b68-abd3-499e-ae8b-d6ab5f1f4012",
            "identity": "Car",
            "x0": 354.91,
            "y0": 181.95,
            "x1": 477.47,
            "y1": 224.07,
            "attributes": {
                "sandbox_tags": [
                    {
                        "original_agent_height": "1.47",
                        "original_agent_width": "1.53"
                    }
                ]
            },
            "sub_entities": []
        },
        {
            "agent_img_id": "agent_2",
            "uuid": "ed146b9e-0cb9-4a90-a349-07d1a2e922a8",
            "identity": "Car",
            "x0": 643.29,
            "y0": 177.49,
            "x1": 710.08,
            "y1": 231.96,
            "attributes": {
                "sandbox_tags": [
                    {
                        "original_agent_height": "1.64",
                        "original_agent_width": "1.62"
                    }
                ]
            },
            "sub_entities": []
        },
        {
            "agent_img_id": "agent_3",
            "uuid": "453412bf-95be-4aec-9643-d84c03d7fc41",
            "identity": "Car",
            "x0": 468.06,
            "y0": 187.84,
            "x1": 538.8,
            "y1": 242.41,
            "attributes": {
                "sandbox_tags": [
                    {
                        "original_agent_height": "1.35",
                        "original_agent_width": "1.47"
                    }
                ]
            },
            "sub_entities": []
        },
        {
            "agent_img_id": "agent_4",
            "uuid": "f375e1dc-b3f9-44c8-b41c-ae9055cb6163",
            "identity": "Car",
            "x0": 3.63,
            "y0": 180.81,
            "x1": 339.48,
            "y1": 287.48,
            "attributes": {
                "sandbox_tags": [
                    {
                        "original_agent_height": "1.48",
                        "original_agent_width": "1.61"
                    }
                ]
            },
            "sub_entities": []
        },
        {
            "agent_img_id": "agent_5",
            "uuid": "d939fe9b-0299-4176-8736-4cdab6f881b9",
            "identity": "Car",
            "x0": 0.0,
            "y0": 185.86,
            "x1": 259.89,
            "y1": 323.48,
            "attributes": {
                "sandbox_tags": [
                    {
                        "original_agent_height": "1.50",
                        "original_agent_width": "1.80"
                    }
                ]
            },
            "sub_entities": []
        },
        {
            "agent_img_id": "agent_6",
            "uuid": "4fc42fb3-7dcc-4209-87bf-9a53c578a537",
            "identity": "Car",
            "x0": 789.35,
            "y0": 210.34,
            "x1": 1241.0,
            "y1": 374.0,
            "attributes": {
                "sandbox_tags": [
                    {
                        "original_agent_height": "1.27",
                        "original_agent_width": "1.58"
                    }
                ]
            },
            "sub_entities": []
        },
        {
            "agent_img_id": "agent_7",
            "uuid": "f06a1faa-460b-4485-94b2-e7723ef31856",
            "identity": "DontCare",
            "x0": 610.6,
            "y0": 178.15,
            "x1": 637.73,
            "y1": 200.07,
            "attributes": {
                "sandbox_tags": [
                    {
                        "original_agent_height": "-1",
                        "original_agent_width": "-1"
                    }
                ]
            },
            "sub_entities": []
        },
        {
            "agent_img_id": "agent_8",
            "uuid": "d2d6a8d8-29b4-40a7-987d-8966ca35fed0",
            "identity": "DontCare",
            "x0": 486.65,
            "y0": 178.15,
            "x1": 596.07,
            "y1": 192.78,
            "attributes": {
                "sandbox_tags": [
                    {
                        "original_agent_height": "-1",
                        "original_agent_width": "-1"
                    }
                ]
            },
            "sub_entities": []
        }
    ]
}