{
    "im_name": "marseille_01357.png",
    "city_name": "marseille",
    "im_width": 1920,
    "im_height": 1024,
    "sandbox_tags": [],
    "agents": [
        {
            "agent_img_id": "agent_1",
            "uuid": "0fdea84d-e1e2-4729-b986-cf391cec8f71",
            "identity": "person-group-far-away",
            "x0": 926,
            "y0": 412,
            "x1": 934,
            "y1": 432,
            "attributes": {
                "sandbox_tags": []
            },
            "sub_entities": []
        },
        {
            "agent_img_id": "agent_2",
            "uuid": "7b327f72-fcc6-4485-aa19-3818c667f26c",
            "identity": "pedestrian",
            "x0": 1233,
            "y0": 400,
            "x1": 1261,
            "y1": 483,
            "attributes": {
                "sandbox_tags": [
                    "occluded>40"
                ]
            },
            "sub_entities": []
        }
    ]
}