{
    "im_name":"bochum_000000_024717_leftImg8bit.png", 
    "cityname":"bochum", 
    "bbs":{
        "agent_1":{
            "class_label":0, 
            "x1":1267, 
            "y1":432, 
            "w":10, 
            "h":9, 
            "instance_id":9, 
            "x1_vis":0, 
            "y1_vis":1267, 
            "w_vis":432, 
            "h_vis":10
        }, 
        "agent_2":{
            "class_label":0, 
            "x1":127, 
            "y1":409, 
            "w":11, 
            "h":15, 
            "instance_id":15, 
            "x1_vis":0, 
            "y1_vis":127, 
            "w_vis":409, 
            "h_vis":11
        }
    }
}