{
    "im_name":"bremen_000146_000019_leftImg8bit.png", 
    "cityname":"bremen", 
    "bbs":{
        "agent_1":{
            "class_label":2, 
            "x1":481, 
            "y1":365, 
            "w":50, 
            "h":121, 
            "instance_id":121, 
            "x1_vis":25000, 
            "y1_vis":522, 
            "w_vis":383, 
            "h_vis":9
        }, 
        "agent_2":{
            "class_label":0, 
            "x1":705, 
            "y1":382, 
            "w":44, 
            "h":60, 
            "instance_id":60, 
            "x1_vis":0, 
            "y1_vis":705, 
            "w_vis":382, 
            "h_vis":44
        }, 
        "agent_3":{
            "class_label":0, 
            "x1":847, 
            "y1":394, 
            "w":41, 
            "h":36, 
            "instance_id":36, 
            "x1_vis":0, 
            "y1_vis":847, 
            "w_vis":394, 
            "h_vis":41
        }, 
        "agent_4":{
            "class_label":0, 
            "x1":226, 
            "y1":380, 
            "w":14, 
            "h":67, 
            "instance_id":67, 
            "x1_vis":0, 
            "y1_vis":226, 
            "w_vis":380, 
            "h_vis":14
        }, 
        "agent_5":{
            "class_label":0, 
            "x1":521, 
            "y1":366, 
            "w":16, 
            "h":85, 
            "instance_id":85, 
            "x1_vis":0, 
            "y1_vis":521, 
            "w_vis":366, 
            "h_vis":16
        }
    }
}