{
    "im_name":"erfurt_000046_000019_leftImg8bit.png", 
    "cityname":"erfurt", 
    "bbs":{
        "agent_1":{
            "class_label":1, 
            "x1":697, 
            "y1":397, 
            "w":62, 
            "h":151, 
            "instance_id":151, 
            "x1_vis":24000, 
            "y1_vis":700, 
            "w_vis":397, 
            "h_vis":53
        }, 
        "agent_2":{
            "class_label":1, 
            "x1":1140, 
            "y1":400, 
            "w":38, 
            "h":92, 
            "instance_id":92, 
            "x1_vis":24001, 
            "y1_vis":1150, 
            "w_vis":402, 
            "h_vis":25
        }, 
        "agent_3":{
            "class_label":1, 
            "x1":1120, 
            "y1":409, 
            "w":33, 
            "h":82, 
            "instance_id":82, 
            "x1_vis":24002, 
            "y1_vis":1122, 
            "w_vis":410, 
            "h_vis":30
        }
    }
}