{
    "im_name": "koeln_00193.png",
    "city_name": "koeln",
    "im_width": 1920,
    "im_height": 1024,
    "sandbox_tags": [],
    "agents": [
        {
            "agent_img_id": "agent_1",
            "uuid": "988d4388-f2f8-48f5-bec9-aafb8aef5165",
            "identity": "pedestrian",
            "x0": 760,
            "y0": 513,
            "x1": 805,
            "y1": 642,
            "attributes": {
                "sandbox_tags": []
            },
            "sub_entities": []
        },
        {
            "agent_img_id": "agent_2",
            "uuid": "6230d51f-4685-4dd9-9165-feb05e40ea61",
            "identity": "pedestrian",
            "x0": 773,
            "y0": 504,
            "x1": 815,
            "y1": 641,
            "attributes": {
                "sandbox_tags": [
                    "occluded>10"
                ]
            },
            "sub_entities": []
        },
        {
            "agent_img_id": "agent_3",
            "uuid": "0715d2b3-c1bc-42d3-989e-03006e5a0542",
            "identity": "pedestrian",
            "x0": 807,
            "y0": 505,
            "x1": 836,
            "y1": 644,
            "attributes": {
                "sandbox_tags": []
            },
            "sub_entities": []
        },
        {
            "agent_img_id": "agent_4",
            "uuid": "e9a67e9a-c2f4-426d-a919-f790faf2fef9",
            "identity": "pedestrian",
            "x0": 833,
            "y0": 513,
            "x1": 863,
            "y1": 637,
            "attributes": {
                "sandbox_tags": []
            },
            "sub_entities": []
        },
        {
            "agent_img_id": "agent_5",
            "uuid": "7c5528ad-c41a-4bb0-92e0-006e6dcfe71e",
            "identity": "pedestrian",
            "x0": 860,
            "y0": 516,
            "x1": 890,
            "y1": 642,
            "attributes": {
                "sandbox_tags": []
            },
            "sub_entities": []
        },
        {
            "agent_img_id": "agent_6",
            "uuid": "92a6d2ec-eef2-4318-aac5-80355f985ec3",
            "identity": "pedestrian",
            "x0": 889,
            "y0": 507,
            "x1": 932,
            "y1": 640,
            "attributes": {
                "sandbox_tags": []
            },
            "sub_entities": []
        },
        {
            "agent_img_id": "agent_7",
            "uuid": "c7e5dde1-fa34-4002-8b51-c7b3af91cf0a",
            "identity": "person-group-far-away",
            "x0": 1154,
            "y0": 539,
            "x1": 1170,
            "y1": 557,
            "attributes": {
                "sandbox_tags": []
            },
            "sub_entities": []
        },
        {
            "agent_img_id": "agent_8",
            "uuid": "b51fd3b1-35f9-41b6-87e2-a972f0522b2e",
            "identity": "pedestrian",
            "x0": 1279,
            "y0": 533,
            "x1": 1294,
            "y1": 570,
            "attributes": {
                "sandbox_tags": [
                    "occluded>40"
                ]
            },
            "sub_entities": []
        },
        {
            "agent_img_id": "agent_9",
            "uuid": "2b5141a7-0629-47a2-b99b-284059f8fb2a",
            "identity": "pedestrian",
            "x0": 1311,
            "y0": 531,
            "x1": 1323,
            "y1": 569,
            "attributes": {
                "sandbox_tags": [
                    "occluded>40"
                ]
            },
            "sub_entities": []
        },
        {
            "agent_img_id": "agent_10",
            "uuid": "07424641-18df-4566-b8c1-cf799a9a0ab1",
            "identity": "pedestrian",
            "x0": 1806,
            "y0": 500,
            "x1": 1856,
            "y1": 657,
            "attributes": {
                "sandbox_tags": [
                    "occluded>80",
                    "unsure_orientation"
                ]
            },
            "sub_entities": []
        },
        {
            "agent_img_id": "agent_11",
            "uuid": "e4aba64b-caf6-4a29-830f-c315931ff159",
            "identity": "pedestrian",
            "x0": 1758,
            "y0": 526,
            "x1": 1787,
            "y1": 611,
            "attributes": {
                "sandbox_tags": [
                    "occluded>40"
                ]
            },
            "sub_entities": []
        },
        {
            "agent_img_id": "agent_12",
            "uuid": "72fd4ce8-a9df-43a5-ae9b-6b60632b437a",
            "identity": "person-group-far-away",
            "x0": 1036,
            "y0": 544,
            "x1": 1044,
            "y1": 562,
            "attributes": {
                "sandbox_tags": []
            },
            "sub_entities": []
        },
        {
            "agent_img_id": "agent_13",
            "uuid": "b04bd05f-c70c-436d-b301-d713f3d9ebe6",
            "identity": "person-group-far-away",
            "x0": 1337,
            "y0": 524,
            "x1": 1350,
            "y1": 560,
            "attributes": {
                "sandbox_tags": []
            },
            "sub_entities": []
        },
        {
            "agent_img_id": "agent_14",
            "uuid": "e8c58563-3a57-4a19-a8aa-e4364962c9ad",
            "identity": "person-group-far-away",
            "x0": 1146,
            "y0": 540,
            "x1": 1152,
            "y1": 555,
            "attributes": {
                "sandbox_tags": []
            },
            "sub_entities": []
        },
        {
            "agent_img_id": "agent_15",
            "uuid": "18402e38-d096-465a-b353-ca0a80aa4995",
            "identity": "person-group-far-away",
            "x0": 859,
            "y0": 507,
            "x1": 910,
            "y1": 632,
            "attributes": {
                "sandbox_tags": []
            },
            "sub_entities": []
        },
        {
            "agent_img_id": "agent_16",
            "uuid": "58cc2707-6788-4aa6-94ec-7ff2ab991866",
            "identity": "person-group-far-away",
            "x0": 1174,
            "y0": 538,
            "x1": 1184,
            "y1": 564,
            "attributes": {
                "sandbox_tags": []
            },
            "sub_entities": []
        },
        {
            "agent_img_id": "agent_17",
            "uuid": "e8afd9ea-8848-4aa1-8678-34e0ec2dd1df",
            "identity": "person-group-far-away",
            "x0": 1287,
            "y0": 535,
            "x1": 1305,
            "y1": 567,
            "attributes": {
                "sandbox_tags": []
            },
            "sub_entities": []
        }
    ]
}