{
    "im_name": "roma_01167.png",
    "city_name": "roma",
    "im_width": 1920,
    "im_height": 1024,
    "sandbox_tags": [],
    "agents": [
        {
            "agent_img_id": "agent_1",
            "uuid": "1d5d2e2b-6895-409c-94c9-6d43a68a6946",
            "identity": "person-group-far-away",
            "x0": 390,
            "y0": 527,
            "x1": 413,
            "y1": 594,
            "attributes": {
                "sandbox_tags": []
            },
            "sub_entities": []
        },
        {
            "agent_img_id": "agent_2",
            "uuid": "cf8c26d3-527a-48ae-8909-5894bc950f59",
            "identity": "person-group-far-away",
            "x0": 629,
            "y0": 541,
            "x1": 657,
            "y1": 605,
            "attributes": {
                "sandbox_tags": []
            },
            "sub_entities": []
        },
        {
            "agent_img_id": "agent_3",
            "uuid": "30d0187e-a24a-49e8-854e-3f9c39a254c8",
            "identity": "pedestrian",
            "x0": 617,
            "y0": 543,
            "x1": 643,
            "y1": 608,
            "attributes": {
                "sandbox_tags": []
            },
            "sub_entities": []
        },
        {
            "agent_img_id": "agent_4",
            "uuid": "e2469be4-4435-4946-818c-e662a9ba5966",
            "identity": "person-group-far-away",
            "x0": 678,
            "y0": 530,
            "x1": 727,
            "y1": 625,
            "attributes": {
                "sandbox_tags": []
            },
            "sub_entities": []
        },
        {
            "agent_img_id": "agent_5",
            "uuid": "2137c039-f268-45a1-8da3-9a1af0865eb9",
            "identity": "pedestrian",
            "x0": 655,
            "y0": 536,
            "x1": 682,
            "y1": 625,
            "attributes": {
                "sandbox_tags": [
                    "occluded>10"
                ]
            },
            "sub_entities": []
        },
        {
            "agent_img_id": "agent_6",
            "uuid": "acf80a72-404a-4597-a837-a75ba9247600",
            "identity": "pedestrian",
            "x0": 343,
            "y0": 516,
            "x1": 407,
            "y1": 648,
            "attributes": {
                "sandbox_tags": [
                    "occluded>80",
                    "unsure_orientation"
                ]
            },
            "sub_entities": []
        },
        {
            "agent_img_id": "agent_7",
            "uuid": "cce38b55-7658-44bd-87c7-5e644f31b9eb",
            "identity": "pedestrian",
            "x0": 349,
            "y0": 521,
            "x1": 389,
            "y1": 659,
            "attributes": {
                "sandbox_tags": [
                    "occluded>10"
                ]
            },
            "sub_entities": []
        },
        {
            "agent_img_id": "agent_8",
            "uuid": "12479724-e427-4617-ad75-4c5e6915cb0d",
            "identity": "pedestrian",
            "x0": 437,
            "y0": 537,
            "x1": 492,
            "y1": 651,
            "attributes": {
                "sandbox_tags": [
                    "occluded>10"
                ]
            },
            "sub_entities": []
        },
        {
            "agent_img_id": "agent_9",
            "uuid": "9fb4bc3e-150e-4c8c-9ff2-55e489c9a2c6",
            "identity": "pedestrian",
            "x0": 470,
            "y0": 517,
            "x1": 522,
            "y1": 655,
            "attributes": {
                "sandbox_tags": []
            },
            "sub_entities": []
        },
        {
            "agent_img_id": "agent_10",
            "uuid": "8a0fffa1-b2cf-4109-b12d-c58146e9c9ed",
            "identity": "person-group-far-away",
            "x0": 735,
            "y0": 546,
            "x1": 771,
            "y1": 584,
            "attributes": {
                "sandbox_tags": []
            },
            "sub_entities": []
        },
        {
            "agent_img_id": "agent_11",
            "uuid": "dfda3b34-3a9d-4309-aa2b-c693d7a34584",
            "identity": "pedestrian",
            "x0": 764,
            "y0": 546,
            "x1": 786,
            "y1": 607,
            "attributes": {
                "sandbox_tags": []
            },
            "sub_entities": []
        },
        {
            "agent_img_id": "agent_12",
            "uuid": "14d0110f-5866-4647-b306-7650af8a25cc",
            "identity": "person-group-far-away",
            "x0": 926,
            "y0": 557,
            "x1": 939,
            "y1": 587,
            "attributes": {
                "sandbox_tags": []
            },
            "sub_entities": []
        },
        {
            "agent_img_id": "agent_13",
            "uuid": "338c80ce-ab2f-4e43-9882-4c1443a53166",
            "identity": "pedestrian",
            "x0": 847,
            "y0": 531,
            "x1": 894,
            "y1": 655,
            "attributes": {
                "sandbox_tags": []
            },
            "sub_entities": []
        },
        {
            "agent_img_id": "agent_14",
            "uuid": "28f30ea1-2507-47a1-b57f-801a0ee079b4",
            "identity": "pedestrian",
            "x0": 886,
            "y0": 534,
            "x1": 928,
            "y1": 655,
            "attributes": {
                "sandbox_tags": []
            },
            "sub_entities": []
        },
        {
            "agent_img_id": "agent_15",
            "uuid": "afa2458d-ccc0-4f76-8697-f5c66419eb58",
            "identity": "pedestrian",
            "x0": 936,
            "y0": 529,
            "x1": 992,
            "y1": 660,
            "attributes": {
                "sandbox_tags": [
                    "occluded>10"
                ]
            },
            "sub_entities": []
        },
        {
            "agent_img_id": "agent_16",
            "uuid": "e3f9bad6-d5f3-4171-bee5-a4be51dff61d",
            "identity": "pedestrian",
            "x0": 937,
            "y0": 544,
            "x1": 1001,
            "y1": 666,
            "attributes": {
                "sandbox_tags": [
                    "occluded>10"
                ]
            },
            "sub_entities": []
        },
        {
            "agent_img_id": "agent_17",
            "uuid": "7a7b6e2a-8df1-46b7-b3e3-955e4480fb80",
            "identity": "person-group-far-away",
            "x0": 1144,
            "y0": 553,
            "x1": 1161,
            "y1": 608,
            "attributes": {
                "sandbox_tags": []
            },
            "sub_entities": []
        },
        {
            "agent_img_id": "agent_18",
            "uuid": "5a5ebcff-fbc2-4d97-a151-fdeb7e1ebc31",
            "identity": "pedestrian",
            "x0": 1168,
            "y0": 545,
            "x1": 1190,
            "y1": 611,
            "attributes": {
                "sandbox_tags": [
                    "occluded>10"
                ]
            },
            "sub_entities": []
        },
        {
            "agent_img_id": "agent_19",
            "uuid": "f04bd122-a13b-4c6b-ab13-865b3ad02189",
            "identity": "pedestrian",
            "x0": 1355,
            "y0": 535,
            "x1": 1399,
            "y1": 639,
            "attributes": {
                "sandbox_tags": []
            },
            "sub_entities": []
        },
        {
            "agent_img_id": "agent_20",
            "uuid": "0d6418e3-66a9-4ca6-a817-8ddbdb059a9c",
            "identity": "pedestrian",
            "x0": 1330,
            "y0": 549,
            "x1": 1360,
            "y1": 639,
            "attributes": {
                "sandbox_tags": []
            },
            "sub_entities": []
        },
        {
            "agent_img_id": "agent_21",
            "uuid": "96a5c3fc-ee65-4b4a-86af-d323420dd5ad",
            "identity": "pedestrian",
            "x0": 1218,
            "y0": 555,
            "x1": 1239,
            "y1": 638,
            "attributes": {
                "sandbox_tags": [
                    "occluded>40"
                ]
            },
            "sub_entities": []
        },
        {
            "agent_img_id": "agent_22",
            "uuid": "8ec9c031-8809-48e3-ad8a-1db9420c5988",
            "identity": "pedestrian",
            "x0": 1197,
            "y0": 557,
            "x1": 1229,
            "y1": 662,
            "attributes": {
                "sandbox_tags": []
            },
            "sub_entities": []
        },
        {
            "agent_img_id": "agent_23",
            "uuid": "b3dc6143-1b8d-4701-b783-a8bd041e1f1c",
            "identity": "person-group-far-away",
            "x0": 1249,
            "y0": 548,
            "x1": 1273,
            "y1": 634,
            "attributes": {
                "sandbox_tags": []
            },
            "sub_entities": []
        },
        {
            "agent_img_id": "agent_24",
            "uuid": "2447839a-417f-4147-bbf0-c02f1b56d866",
            "identity": "person-group-far-away",
            "x0": 1280,
            "y0": 546,
            "x1": 1301,
            "y1": 632,
            "attributes": {
                "sandbox_tags": []
            },
            "sub_entities": []
        },
        {
            "agent_img_id": "agent_25",
            "uuid": "a2142507-4d31-43cf-9014-06dbbf28cb6a",
            "identity": "pedestrian",
            "x0": 1298,
            "y0": 548,
            "x1": 1333,
            "y1": 643,
            "attributes": {
                "sandbox_tags": [
                    "occluded>40"
                ]
            },
            "sub_entities": []
        },
        {
            "agent_img_id": "agent_26",
            "uuid": "cc10f752-95c4-41a1-9850-d83f939159a1",
            "identity": "pedestrian",
            "x0": 1228,
            "y0": 544,
            "x1": 1268,
            "y1": 664,
            "attributes": {
                "sandbox_tags": []
            },
            "sub_entities": []
        },
        {
            "agent_img_id": "agent_27",
            "uuid": "479f0a2b-7f24-4229-8f2a-9ef97269d17d",
            "identity": "pedestrian",
            "x0": 1262,
            "y0": 546,
            "x1": 1299,
            "y1": 642,
            "attributes": {
                "sandbox_tags": [
                    "occluded>40",
                    "unsure_orientation"
                ]
            },
            "sub_entities": []
        },
        {
            "agent_img_id": "agent_28",
            "uuid": "06e784e8-8ab1-4be9-ab70-062f17494d49",
            "identity": "pedestrian",
            "x0": 1241,
            "y0": 557,
            "x1": 1296,
            "y1": 657,
            "attributes": {
                "sandbox_tags": [
                    "occluded>10"
                ]
            },
            "sub_entities": []
        },
        {
            "agent_img_id": "agent_29",
            "uuid": "cc26b405-8908-430b-9b6c-3aac3b9e046c",
            "identity": "rider",
            "x0": 1282,
            "y0": 594,
            "x1": 1308,
            "y1": 641,
            "attributes": {
                "sandbox_tags": []
            },
            "sub_entities": [
                {
                    "identity": "buggy",
                    "x0": 1272,
                    "y0": 584,
                    "x1": 1312,
                    "y1": 654,
                    "attributes": {
                        "sandbox_tags": []
                    }
                }
            ]
        },
        {
            "agent_img_id": "agent_30",
            "uuid": "c6f7f831-f799-43df-accd-6c3a83a12110",
            "identity": "pedestrian",
            "x0": 682,
            "y0": 527,
            "x1": 719,
            "y1": 643,
            "attributes": {
                "sandbox_tags": []
            },
            "sub_entities": []
        },
        {
            "agent_img_id": "agent_31",
            "uuid": "6d722b90-f93a-4f62-9ae6-aa3709ec78ec",
            "identity": "pedestrian",
            "x0": 417,
            "y0": 553,
            "x1": 448,
            "y1": 644,
            "attributes": {
                "sandbox_tags": []
            },
            "sub_entities": []
        },
        {
            "agent_img_id": "agent_32",
            "uuid": "130d9e29-e893-4619-affd-069a721f4dd8",
            "identity": "pedestrian",
            "x0": 1299,
            "y0": 549,
            "x1": 1340,
            "y1": 652,
            "attributes": {
                "sandbox_tags": []
            },
            "sub_entities": []
        },
        {
            "agent_img_id": "agent_33",
            "uuid": "cd78e90e-0ed1-4072-bf2e-aafe9b7bc18f",
            "identity": "pedestrian",
            "x0": 403,
            "y0": 529,
            "x1": 421,
            "y1": 596,
            "attributes": {
                "sandbox_tags": []
            },
            "sub_entities": []
        },
        {
            "agent_img_id": "agent_34",
            "uuid": "f239dca4-b90b-4204-8845-aaf318afc54c",
            "identity": "pedestrian",
            "x0": 422,
            "y0": 529,
            "x1": 444,
            "y1": 590,
            "attributes": {
                "sandbox_tags": [
                    "occluded>40",
                    "unsure_orientation"
                ]
            },
            "sub_entities": []
        },
        {
            "agent_img_id": "agent_35",
            "uuid": "10774f23-899c-4ad1-bc3a-566ad068eacf",
            "identity": "pedestrian",
            "x0": 506,
            "y0": 533,
            "x1": 526,
            "y1": 601,
            "attributes": {
                "sandbox_tags": [
                    "occluded>40"
                ]
            },
            "sub_entities": []
        },
        {
            "agent_img_id": "agent_36",
            "uuid": "56844911-fecb-49a7-94b5-4d757b5c3436",
            "identity": "pedestrian",
            "x0": 520,
            "y0": 539,
            "x1": 537,
            "y1": 601,
            "attributes": {
                "sandbox_tags": [
                    "occluded>10"
                ]
            },
            "sub_entities": []
        },
        {
            "agent_img_id": "agent_37",
            "uuid": "39cb5432-696e-44e1-aa96-462e9df1dc1f",
            "identity": "pedestrian",
            "x0": 578,
            "y0": 537,
            "x1": 599,
            "y1": 600,
            "attributes": {
                "sandbox_tags": [
                    "occluded>10"
                ]
            },
            "sub_entities": []
        }
    ]
}