{
    "im_name": "berlin_00439.png",
    "city_name": "berlin",
    "im_width": 1920,
    "im_height": 1024,
    "sandbox_tags": [],
    "agents": [
        {
            "agent_img_id": "agent_1",
            "uuid": "d28e926b-f3ff-4a08-850f-1d450c6761b3",
            "identity": "person-group-far-away",
            "x0": 117,
            "y0": 553,
            "x1": 137,
            "y1": 610,
            "attributes": {
                "sandbox_tags": []
            },
            "sub_entities": []
        },
        {
            "agent_img_id": "agent_2",
            "uuid": "f2546e85-6622-45d8-b68e-df3f679c4c24",
            "identity": "person-group-far-away",
            "x0": 222,
            "y0": 557,
            "x1": 236,
            "y1": 601,
            "attributes": {
                "sandbox_tags": []
            },
            "sub_entities": []
        },
        {
            "agent_img_id": "agent_3",
            "uuid": "80382e99-fa39-4898-a5ca-3d461cd41648",
            "identity": "buggy-group",
            "x0": 631,
            "y0": 568,
            "x1": 705,
            "y1": 672,
            "attributes": {
                "sandbox_tags": []
            },
            "sub_entities": []
        },
        {
            "agent_img_id": "agent_4",
            "uuid": "aaa8b328-f631-42ba-a74e-290724e66ac5",
            "identity": "pedestrian",
            "x0": 673,
            "y0": 496,
            "x1": 731,
            "y1": 684,
            "attributes": {
                "sandbox_tags": [
                    "occluded>10"
                ]
            },
            "sub_entities": []
        },
        {
            "agent_img_id": "agent_5",
            "uuid": "1a3b5de0-8905-4c99-975c-62245bee579e",
            "identity": "pedestrian",
            "x0": 595,
            "y0": 488,
            "x1": 642,
            "y1": 698,
            "attributes": {
                "sandbox_tags": [
                    "occluded>40"
                ]
            },
            "sub_entities": []
        },
        {
            "agent_img_id": "agent_6",
            "uuid": "56519faa-a6ac-4a39-a640-f998c2a99a0d",
            "identity": "pedestrian",
            "x0": 540,
            "y0": 522,
            "x1": 634,
            "y1": 704,
            "attributes": {
                "sandbox_tags": [
                    "occluded>40"
                ]
            },
            "sub_entities": []
        },
        {
            "agent_img_id": "agent_7",
            "uuid": "f457dbb6-f439-4b4e-ba82-10219bcb0f6b",
            "identity": "pedestrian",
            "x0": 1248,
            "y0": 509,
            "x1": 1284,
            "y1": 621,
            "attributes": {
                "sandbox_tags": [
                    "occluded>10"
                ]
            },
            "sub_entities": []
        },
        {
            "agent_img_id": "agent_8",
            "uuid": "4ce57d00-f6c1-488c-b9ae-4f9dd3610546",
            "identity": "person-group-far-away",
            "x0": 1441,
            "y0": 509,
            "x1": 1464,
            "y1": 566,
            "attributes": {
                "sandbox_tags": []
            },
            "sub_entities": []
        },
        {
            "agent_img_id": "agent_9",
            "uuid": "c47236ee-a788-4742-903a-f200e9f74234",
            "identity": "person-group-far-away",
            "x0": 1812,
            "y0": 458,
            "x1": 1915,
            "y1": 651,
            "attributes": {
                "sandbox_tags": []
            },
            "sub_entities": []
        },
        {
            "agent_img_id": "agent_10",
            "uuid": "78cffd92-d195-4f4d-8a15-0a3ac8438123",
            "identity": "person-group-far-away",
            "x0": 1219,
            "y0": 526,
            "x1": 1241,
            "y1": 583,
            "attributes": {
                "sandbox_tags": []
            },
            "sub_entities": []
        }
    ]
}