{
    "im_name": "stuttgart_000102_000019_leftImg8bit.png",
    "city_name": "stuttgart",
    "im_width": 2048,
    "im_height": 1024,
    "sandbox_tags": [],
    "agents": [
        {
            "agent_img_id": "agent_1",
            "uuid": "ef502941-6747-43a2-8be4-73f96a1cf225",
            "identity": "Pedestrian",
            "x0": 830,
            "y0": 419,
            "x1": 854,
            "y1": 477,
            "attributes": {
                "sandbox_tags": []
            },
            "sub_entities": []
        },
        {
            "agent_img_id": "agent_2",
            "uuid": "e3df90cd-cb52-451f-8053-b9d85c332cd9",
            "identity": "Pedestrian",
            "x0": 867,
            "y0": 420,
            "x1": 890,
            "y1": 476,
            "attributes": {
                "sandbox_tags": []
            },
            "sub_entities": []
        },
        {
            "agent_img_id": "agent_3",
            "uuid": "c7d05249-38c6-4c07-b927-032649f7c306",
            "identity": "Pedestrian",
            "x0": 816,
            "y0": 418,
            "x1": 839,
            "y1": 475,
            "attributes": {
                "sandbox_tags": []
            },
            "sub_entities": []
        },
        {
            "agent_img_id": "agent_4",
            "uuid": "b6e72040-ddf3-4a2c-b0b5-bb92653069b2",
            "identity": "Pedestrian",
            "x0": 1420,
            "y0": 367,
            "x1": 1481,
            "y1": 515,
            "attributes": {
                "sandbox_tags": []
            },
            "sub_entities": []
        },
        {
            "agent_img_id": "agent_5",
            "uuid": "b47c8384-ea11-4d86-8c34-3b1c2ae0588b",
            "identity": "Pedestrian",
            "x0": 530,
            "y0": 408,
            "x1": 574,
            "y1": 514,
            "attributes": {
                "sandbox_tags": []
            },
            "sub_entities": []
        },
        {
            "agent_img_id": "agent_6",
            "uuid": "7b4ae8a9-ae2f-46b0-bc8e-e55e22543731",
            "identity": "Pedestrian",
            "x0": 482,
            "y0": 396,
            "x1": 529,
            "y1": 512,
            "attributes": {
                "sandbox_tags": []
            },
            "sub_entities": []
        },
        {
            "agent_img_id": "agent_7",
            "uuid": "044862bd-5c1a-436f-9521-f2819b4534e7",
            "identity": "Pedestrian",
            "x0": 343,
            "y0": 388,
            "x1": 412,
            "y1": 556,
            "attributes": {
                "sandbox_tags": []
            },
            "sub_entities": []
        },
        {
            "agent_img_id": "agent_8",
            "uuid": "ff72d4f1-d073-4dcd-a926-b1c31172cab6",
            "identity": "Pedestrian",
            "x0": 847,
            "y0": 417,
            "x1": 871,
            "y1": 476,
            "attributes": {
                "sandbox_tags": []
            },
            "sub_entities": []
        },
        {
            "agent_img_id": "agent_9",
            "uuid": "8c2b1d5a-b47f-4762-aa38-c6f01893d9ef",
            "identity": "Ignore",
            "x0": 1165,
            "y0": 388,
            "x1": 1172,
            "y1": 399,
            "attributes": {
                "sandbox_tags": []
            },
            "sub_entities": []
        },
        {
            "agent_img_id": "agent_10",
            "uuid": "449f6817-150a-427b-b87b-56f6ae785a8c",
            "identity": "Ignore",
            "x0": 1102,
            "y0": 414,
            "x1": 1109,
            "y1": 433,
            "attributes": {
                "sandbox_tags": []
            },
            "sub_entities": []
        }
    ]
}