{
    "im_name": "stuttgart_000083_000019_leftImg8bit.png",
    "city_name": "stuttgart",
    "im_width": 2048,
    "im_height": 1024,
    "sandbox_tags": [],
    "agents": [
        {
            "agent_img_id": "agent_1",
            "uuid": "48bbe198-08b6-47d7-91fe-a06959071bd5",
            "identity": "Pedestrian",
            "x0": 186,
            "y0": 436,
            "x1": 236,
            "y1": 558,
            "attributes": {
                "sandbox_tags": []
            },
            "sub_entities": []
        }
    ]
}