{
    "im_name": "pisa_00653.png",
    "city_name": "pisa",
    "im_width": 1920,
    "im_height": 1024,
    "sandbox_tags": [],
    "agents": [
        {
            "agent_img_id": "agent_1",
            "uuid": "33a03f80-c238-45ee-93fb-482c1045771e",
            "identity": "pedestrian",
            "x0": 0,
            "y0": 474,
            "x1": 58,
            "y1": 763,
            "attributes": {
                "sandbox_tags": [
                    "occluded>10",
                    "truncated>40"
                ]
            },
            "sub_entities": []
        },
        {
            "agent_img_id": "agent_2",
            "uuid": "6885a96e-da1d-4653-b4c6-0e1d32cf9b34",
            "identity": "bicycle-group",
            "x0": 0,
            "y0": 632,
            "x1": 409,
            "y1": 1022,
            "attributes": {
                "sandbox_tags": [
                    "truncated>40"
                ]
            },
            "sub_entities": []
        },
        {
            "agent_img_id": "agent_3",
            "uuid": "9b7598cd-7c47-417a-99c8-9bd01ef4c312",
            "identity": "scooter-group",
            "x0": 762,
            "y0": 552,
            "x1": 948,
            "y1": 674,
            "attributes": {
                "sandbox_tags": []
            },
            "sub_entities": []
        },
        {
            "agent_img_id": "agent_4",
            "uuid": "ed41ab5e-79c0-44b8-a201-18df6cb37d5a",
            "identity": "scooter-group",
            "x0": 1123,
            "y0": 567,
            "x1": 1182,
            "y1": 596,
            "attributes": {
                "sandbox_tags": [
                    "occluded>10"
                ]
            },
            "sub_entities": []
        },
        {
            "agent_img_id": "agent_5",
            "uuid": "7cd127b3-9521-4477-9745-b69272695236",
            "identity": "pedestrian",
            "x0": 1176,
            "y0": 537,
            "x1": 1232,
            "y1": 671,
            "attributes": {
                "sandbox_tags": []
            },
            "sub_entities": []
        },
        {
            "agent_img_id": "agent_6",
            "uuid": "fb165454-c530-4837-94af-f6a954a0c79b",
            "identity": "pedestrian",
            "x0": 1246,
            "y0": 543,
            "x1": 1289,
            "y1": 668,
            "attributes": {
                "sandbox_tags": [
                    "occluded>10"
                ]
            },
            "sub_entities": []
        },
        {
            "agent_img_id": "agent_7",
            "uuid": "4985185c-3a8e-4afe-81c3-c9b419841150",
            "identity": "buggy-group",
            "x0": 1425,
            "y0": 576,
            "x1": 1474,
            "y1": 645,
            "attributes": {
                "sandbox_tags": []
            },
            "sub_entities": []
        },
        {
            "agent_img_id": "agent_8",
            "uuid": "6fdb6300-4289-4919-8aca-f923f8ed10e5",
            "identity": "pedestrian",
            "x0": 1440,
            "y0": 529,
            "x1": 1471,
            "y1": 647,
            "attributes": {
                "sandbox_tags": [
                    "occluded>10"
                ]
            },
            "sub_entities": []
        },
        {
            "agent_img_id": "agent_9",
            "uuid": "16f6530c-b8fa-4376-96b6-ca09811ce38b",
            "identity": "pedestrian",
            "x0": 1496,
            "y0": 533,
            "x1": 1530,
            "y1": 648,
            "attributes": {
                "sandbox_tags": [
                    "occluded>40"
                ]
            },
            "sub_entities": []
        },
        {
            "agent_img_id": "agent_10",
            "uuid": "4e3165c0-73b4-47a4-a01f-eac861cf7643",
            "identity": "person-group-far-away",
            "x0": 1128,
            "y0": 556,
            "x1": 1174,
            "y1": 589,
            "attributes": {
                "sandbox_tags": []
            },
            "sub_entities": []
        },
        {
            "agent_img_id": "agent_11",
            "uuid": "9313801c-2672-4f7c-9889-84c821817a68",
            "identity": "person-group-far-away",
            "x0": 1104,
            "y0": 553,
            "x1": 1115,
            "y1": 592,
            "attributes": {
                "sandbox_tags": []
            },
            "sub_entities": []
        }
    ]
}